odoo8_addon_account_reconcile_payment_order-8.0.1.0.1-nspkg.pth
odoo_addons/account_reconcile_payment_order/README.rst
odoo_addons/account_reconcile_payment_order/__init__.py
odoo_addons/account_reconcile_payment_order/__openerp__.py
odoo_addons/account_reconcile_payment_order/i18n/account_reconcile_payment_order.pot
odoo_addons/account_reconcile_payment_order/i18n/de.po
odoo_addons/account_reconcile_payment_order/i18n/fr.po
odoo_addons/account_reconcile_payment_order/i18n/it.po
odoo_addons/account_reconcile_payment_order/i18n/nl_NL.po
odoo_addons/account_reconcile_payment_order/i18n/sl.po
odoo_addons/account_reconcile_payment_order/models/__init__.py
odoo_addons/account_reconcile_payment_order/models/account_bank_statement_line.py
odoo_addons/account_reconcile_payment_order/static/description/icon.png
odoo8_addon_account_reconcile_payment_order-8.0.1.0.1.dist-info/METADATA
odoo8_addon_account_reconcile_payment_order-8.0.1.0.1.dist-info/WHEEL
odoo8_addon_account_reconcile_payment_order-8.0.1.0.1.dist-info/namespace_packages.txt
odoo8_addon_account_reconcile_payment_order-8.0.1.0.1.dist-info/top_level.txt
odoo8_addon_account_reconcile_payment_order-8.0.1.0.1.dist-info/RECORD
