Metadata-Version: 2.1
Name: odoo8-addon-account-reconcile-payment-order
Version: 8.0.1.0.1
Summary: Automatically reconcile all lines from payment orders
Home-page: UNKNOWN
Author: Therp BV,Serv. Tecnol. Avanzados - Pedro M. Baeza,Odoo Community Association (OCA)
Author-email: support@odoo-community.org
License: AGPL-3
Platform: UNKNOWN
Classifier: Programming Language :: Python
Classifier: Framework :: Odoo
Classifier: License :: OSI Approved :: GNU Affero General Public License v3
Requires-Python: ~=2.7
Requires-Dist: odoo8-addon-account-banking-payment-transfer
Requires-Dist: odoo (<9.0a,>=8.0a)
